vital/__init__.py
vital/client.py
vital/core/__init__.py
vital/core/api_error.py
vital/core/client_wrapper.py
vital/core/datetime_utils.py
vital/core/jsonable_encoder.py
vital/core/remove_none_from_dict.py
vital/environment.py
vital/errors/__init__.py
vital/errors/bad_request_error.py
vital/errors/unprocessable_entity_error.py
vital/py.typed
vital/resources/__init__.py
vital/resources/activity/__init__.py
vital/resources/activity/client.py
vital/resources/body/__init__.py
vital/resources/body/client.py
vital/resources/devices/__init__.py
vital/resources/devices/client.py
vital/resources/insurance/__init__.py
vital/resources/insurance/client.py
vital/resources/lab_tests/__init__.py
vital/resources/lab_tests/client.py
vital/resources/link/__init__.py
vital/resources/link/client.py
vital/resources/meal/__init__.py
vital/resources/meal/client.py
vital/resources/profile/__init__.py
vital/resources/profile/client.py
vital/resources/providers/__init__.py
vital/resources/providers/client.py
vital/resources/sleep/__init__.py
vital/resources/sleep/client.py
vital/resources/team/__init__.py
vital/resources/team/client.py
vital/resources/testkit/__init__.py
vital/resources/testkit/client.py
vital/resources/timeseries/__init__.py
vital/resources/timeseries/client.py
vital/resources/user/__init__.py
vital/resources/user/client.py
vital/resources/vitals/__init__.py
vital/resources/vitals/client.py
vital/resources/workouts/__init__.py
vital/resources/workouts/client.py
vital/types/__init__.py
vital/types/activity_v_2_in_db.py
vital/types/address.py
vital/types/appointment_availability_slots.py
vital/types/appointment_event_status.py
vital/types/appointment_provider.py
vital/types/appointment_status.py
vital/types/appointment_type.py
vital/types/area_info.py
vital/types/auth_type.py
vital/types/biomarker_result.py
vital/types/body_v_2_in_db.py
vital/types/client_activity_response.py
vital/types/client_body_response.py
vital/types/client_facing_activity.py
fern_vital-0.2.87.dist-info/METADATA
fern_vital-0.2.87.dist-info/WHEEL
fern_vital-0.2.87.dist-info/RECORD
